okit/__init__.py
okit/py.typed
okit/cli/__init__.py
okit/cli/main.py
okit/core/__init__.py
okit/core/autoreg.py
okit/core/base_tool.py
okit/core/completion.py
okit/core/tool_decorator.py
okit/tools/__init__.py
okit/tools/clonerepos.py
okit/tools/gitdiffsync.py
okit/tools/hexdump.py
okit/tools/minimal_example.py
okit/tools/mobaxterm_colors.py
okit/tools/mobaxterm_pro.py
okit/tools/pedump.py
okit/tools/shellconfig.py
okit/utils/log.py
okit/utils/mobaxterm_detector.py
okit/utils/perf_monitor.py
okit/utils/perf_report.py
okit/utils/timing.py
okit/utils/version.py
okit-1.2.3.dist-info/METADATA
okit-1.2.3.dist-info/WHEEL
okit-1.2.3.dist-info/entry_points.txt
okit-1.2.3.dist-info/licenses/LICENSE
okit-1.2.3.dist-info/RECORD
