Metadata-Version: 2.4
Name: okit
Version: 1.2.3
Summary: OK Kit
Project-URL: Homepage, https://github.com/fjzhangZzzzzz/okit
Project-URL: Documentation, https://github.com/fjzhangZzzzzz/okit
Project-URL: Repository, https://github.com/fjzhangZzzzzz/okit
Project-URL: Issues, https://github.com/fjzhangZzzzzz/okit/issues
Author-email: fjzhang <fjzhang_@outlook.com>
License: MIT
License-File: LICENSE
Classifier: Development Status :: 3 - Alpha
Classifier: Intended Audience :: Developers
Classifier: License :: OSI Approved :: MIT License
Classifier: Operating System :: OS Independent
Classifier: Programming Language :: Python :: 3
Classifier: Programming Language :: Python :: 3.8
Classifier: Programming Language :: Python :: 3.9
Classifier: Programming Language :: Python :: 3.10
Classifier: Programming Language :: Python :: 3.11
Classifier: Programming Language :: Python :: 3.12
Classifier: Topic :: Software Development :: Libraries :: Python Modules
Classifier: Topic :: System :: Systems Administration
Classifier: Topic :: Utilities
Requires-Python: <3.12,>=3.8
Requires-Dist: click>=8.1.0
Requires-Dist: gitpython>=3.1.0
Requires-Dist: paramiko~=3.4
Requires-Dist: psutil>=7.0.0
Requires-Dist: rich>=13.0.0
Requires-Dist: ruamel-yaml>=0.18.0
Provides-Extra: dev
Requires-Dist: black>=23.0.0; extra == 'dev'
Requires-Dist: isort>=5.12.0; extra == 'dev'
Requires-Dist: mypy>=1.0.0; extra == 'dev'
Requires-Dist: pre-commit>=3.0.0; extra == 'dev'
Requires-Dist: pytest-cov==4.1.0; extra == 'dev'
Requires-Dist: pytest==7.4.4; extra == 'dev'
Requires-Dist: ruff>=0.1.0; extra == 'dev'
Requires-Dist: types-paramiko>=3.4.0; extra == 'dev'
Requires-Dist: types-psutil>=5.9.0; extra == 'dev'
Requires-Dist: types-pyyaml>=6.0.0; extra == 'dev'
